pyvcam/__init__.py
pyvcam/camera.py
pyvcam/constants.py
pyvcam/pvc.cpython-314-x86_64-linux-gnu.so
pyvcam/pvcmodule.cpp
pyvcam-2.3.1.dist-info/METADATA
pyvcam-2.3.1.dist-info/WHEEL
pyvcam-2.3.1.dist-info/top_level.txt
pyvcam-2.3.1.dist-info/RECORD
pyvcam-2.3.1.dist-info/licenses/LICENSE
