Metadata-Version: 2.4
Name: PyVCAM
Version: 2.3.1
Summary: Python wrapper for PVCAM functionality
Home-page: https://github.com/Photometrics/PyVCAM
Author: Steve Bellinger, Cameron Smith, Lubomír Walder, Vojtěch Ondřej, Tomáš Hanák
Author-email: Teledyne Photometrics <photometrics.support@teledyne.com>
License-Expression: MIT
Project-URL: homepage, https://github.com/Photometrics/PyVCAM
Project-URL: source, https://github.com/Photometrics/PyVCAM
Project-URL: download, https://pypi.org/project/PyVCAM/#files
Project-URL: tracker, https://github.com/Photometrics/PyVCAM/issues
Keywords: PVCAM,microscopy
Classifier: Development Status :: 5 - Production/Stable
Classifier: Intended Audience :: Science/Research
Classifier: Operating System :: Microsoft :: Windows
Classifier: Operating System :: POSIX :: Linux
Classifier: Programming Language :: Python :: 3 :: Only
Classifier: Programming Language :: Python :: 3.9
Classifier: Programming Language :: Python :: 3.10
Classifier: Programming Language :: Python :: 3.11
Classifier: Programming Language :: Python :: 3.12
Classifier: Programming Language :: Python :: 3.13
Classifier: Programming Language :: Python :: 3.14
Classifier: Topic :: Scientific/Engineering :: Image Processing
Classifier: Topic :: Software Development :: Libraries :: Python Modules
Requires-Python: >=3.9
License-File: LICENSE
Requires-Dist: numpy
Provides-Extra: dev
Requires-Dist: validate-pyproject[all]; extra == "dev"
Requires-Dist: Flake8-pyproject; extra == "dev"
Requires-Dist: flake8-typing-imports; extra == "dev"
Requires-Dist: pylint; extra == "dev"
Dynamic: home-page
Dynamic: license-file
